LICENSE
README.md
pyproject.toml
setup.py
PY_PACKAGE_NAME/__init__.py
PY_PACKAGE_NAME/core.py
PY_PACKAGE_NAME.egg-info/PKG-INFO
PY_PACKAGE_NAME.egg-info/SOURCES.txt
PY_PACKAGE_NAME.egg-info/dependency_links.txt
PY_PACKAGE_NAME.egg-info/entry_points.txt
PY_PACKAGE_NAME.egg-info/requires.txt
PY_PACKAGE_NAME.egg-info/top_level.txt