Metadata-Version: 2.1
Name: PY-PACKAGE-NAME
Version: 0.0.2
Summary: SHORT_DESCRIPTION
Home-page: https://github.com/AUTHOR_NAME/YOUR_PACKAGE_NAME
Author: AUTHOR_NAME
Author-email: AUTHOR_EMAIL@gmail.com
License: MIT License
Classifier: License :: OSI Approved :: Apache Software License
Classifier: Programming Language :: Python :: 3 :: Only
Classifier: Programming Language :: Python :: 3.8
Classifier: Programming Language :: Python :: 3.9
Classifier: Programming Language :: Python :: 3.10
Classifier: Programming Language :: Python :: 3.11
Requires-Python: >=3.8
Provides-Extra: dev
License-File: LICENSE
